LICENSE
README.md
setup.cfg
setup.py
uzbek_latin_cyrillic_converter/__init__.py
uzbek_latin_cyrillic_converter/converter.py
uzbek_latin_cyrillic_converter.egg-info/PKG-INFO
uzbek_latin_cyrillic_converter.egg-info/SOURCES.txt
uzbek_latin_cyrillic_converter.egg-info/dependency_links.txt
uzbek_latin_cyrillic_converter.egg-info/requires.txt
uzbek_latin_cyrillic_converter.egg-info/top_level.txt