Metadata-Version: 2.1
Name: uzbek-latin-cyrillic-converter
Version: 0.2
Summary: A set of tools to convert the text in uzbek between latin and cyrillic
Home-page: https://github.com/Rhtyme/uzbek_latin_cyrillic_converter
Author: Sirojiddin Komolov
Author-email: rhtyme@gmail.com
License: MIT
Keywords: converter,uzbek-latin-cyrillic-converter
Platform: UNKNOWN
